test/__init__.py
test/test_module.py
trumpet_client/__init__.py
trumpet_client/envs.py
trumpet_client/exceptions.py
trumpet_client/api/__init__.py
trumpet_client/api/api_var.py
trumpet_client/api/crud.py
trumpet_client/artifact/__init__.py
trumpet_client/artifact/artifact_handler.py
trumpet_client/artifact/artifact_management.py
trumpet_client/backend/__init__.py
trumpet_client/backend/register_datasets.py
trumpet_client/backend/register_model.py
trumpet_client/config/__init__.py
trumpet_client/config/api_config.py
trumpet_client/config/artifact_config.py
trumpet_client/config/config.py
trumpet_client/config/model_config.py
trumpet_client/config/type_config.py
trumpet_client/launch/__init__.py
trumpet_client/launch/handler.py
trumpet_client/launch/init_datasets.py
trumpet_client/launch/init_model.py
trumpet_client/launch/new_init.py
trumpet_client/launch/user_source_code.py
trumpet_client/loggers/__init__.py
trumpet_client/loggers/_experiment.py
trumpet_client/loggers/experiment.py
trumpet_client/loggers/logger.py
trumpet_client/loggers/system_logging.py
trumpet_client/loggers/tracking_logging.py
trumpet_client/loggers/user_env_logging.py
trumpet_client/management/__init__.py
trumpet_client/management/api_exceptions.py
trumpet_client/management/user_api_management.py
trumpet_client/proto/__init__.py
trumpet_client/proto/parameter_pb2.py
trumpet_client/proto/registerModel_pb2.py
trumpet_client/utils/__init__.py
trumpet_client/utils/api_utils.py
trumpet_client/utils/datetime_utils.py
trumpet_client/utils/decorator.py
trumpet_client/utils/utils.py
trumpet_client-0.0.1.dist-info/METADATA
trumpet_client-0.0.1.dist-info/WHEEL
trumpet_client-0.0.1.dist-info/top_level.txt
trumpet_client-0.0.1.dist-info/RECORD
