Metadata-Version: 2.1
Name: trumpet-client
Version: 0.0.1
Summary: trumpet.ai
Author: trumpet.ai
Project-URL: HOMEPAGE, https://stag.trumpet.ai/
Project-URL: DOCUMENTATION, https://trumpet-ai.gitbook.io/product-docs/
Classifier: Programming Language :: Python :: 3.7
Classifier: Programming Language :: Python :: 3.8
Requires-Python: >=3.6.5
Requires-Dist: coverage
Requires-Dist: requests
Requires-Dist: flake8
Requires-Dist: psutil
Requires-Dist: requests-toolbelt
Requires-Dist: ipykernel
Requires-Dist: jupyter
Requires-Dist: pynvml
Requires-Dist: h5py
Requires-Dist: pandas
